apis_acdhch_django_invite/.gitignore
apis_acdhch_django_invite/__init__.py
apis_acdhch_django_invite/admin.py
apis_acdhch_django_invite/migrations/0001_initial.py
apis_acdhch_django_invite/migrations/__init__.py
apis_acdhch_django_invite/models.py
apis_acdhch_django_invite/signals.py
apis_acdhch_django_invite/templates/invite.html
apis_acdhch_django_invite/urls.py
apis_acdhch_django_invite/views.py
apis_acdhch_django_invite-0.2.0.dist-info/LICENSE
apis_acdhch_django_invite-0.2.0.dist-info/METADATA
apis_acdhch_django_invite-0.2.0.dist-info/WHEEL
apis_acdhch_django_invite-0.2.0.dist-info/RECORD
